[["Map",1,2,9,10,1285,1286],"meta::meta",["Map",3,4,5,6,7,8],"astro-version","5.6.1","content-config-digest","11959a5e661f4042","astro-config-digest","{\"root\":{},\"srcDir\":{},\"publicDir\":{},\"outDir\":{},\"cacheDir\":{},\"site\":\"https://www.veda-egypt.com\",\"compressHTML\":true,\"base\":\"/\",\"trailingSlash\":\"ignore\",\"output\":\"static\",\"scopedStyleStrategy\":\"attribute\",\"build\":{\"format\":\"directory\",\"client\":{},\"server\":{},\"assets\":\"_astro\",\"serverEntry\":\"entry.mjs\",\"redirects\":true,\"inlineStylesheets\":\"auto\",\"concurrency\":1},\"server\":{\"open\":false,\"host\":false,\"port\":4321,\"streaming\":true,\"allowedHosts\":[]},\"redirects\":{},\"image\":{\"endpoint\":{\"route\":\"/_image\"},\"service\":{\"entrypoint\":\"astro/assets/services/sharp\",\"config\":{}},\"domains\":[],\"remotePatterns\":[]},\"devToolbar\":{\"enabled\":true},\"markdown\":{\"syntaxHighlight\":{\"type\":\"shiki\",\"excludeLangs\":[\"math\"]},\"shikiConfig\":{\"langs\":[],\"langAlias\":{},\"theme\":\"github-dark\",\"themes\":{},\"wrap\":false,\"transformers\":[]},\"remarkPlugins\":[],\"rehypePlugins\":[],\"remarkRehype\":{},\"gfm\":true,\"smartypants\":true},\"security\":{\"checkOrigin\":true},\"env\":{\"schema\":{},\"validateSecrets\":false},\"experimental\":{\"clientPrerender\":false,\"contentIntellisense\":false,\"responsiveImages\":false,\"svg\":false,\"serializeConfig\":false,\"headingIdCompat\":false,\"preserveScriptOrder\":false},\"legacy\":{\"collections\":false}}","itineraries",["Map",11,12,142,143,380,381,712,713,743,744,934,935,1204,1205,1232,1233,1259,1260],"3n-4d-aswan-luxor",{"id":11,"data":13,"filePath":140,"digest":141},{"title":14,"summary":15,"description":16,"nights":17,"days":18,"experience":19,"series":20,"vessels":21,"highlights":26,"hero":33,"cardImage":34,"routeOverview":35,"facts":36,"routes":43,"faq":127,"tips":137,"insights":138,"featured":139,"comingSoon":139,"draft":139},"Aswan → Luxor","A short, refined sailing experience for travellers with limited time — the Nile's essential temples, unhurried, in three nights.","Timeless charm meets the gentle rhythm of the river. This express voyage carries you from the island temples of Aswan to the monumental wonders of Luxor, with traditional sailing, curated cuisine, and a daily sunset ritual on deck.",3,4,"Classic Cruise","aswan-luxor-classic",[22,23,24,25],"Veda I","Veda II","Veda III","Veda IV",[27,28,29,30,31,32],"Philae Temple","Kom Ombo","Edfu","Valley of the Kings","Karnak","Luxor Temple","/images/dsc-1797-pano-1280x800.jpg","/images/aswan-temple-1280x800.jpg","Three nights aboard your dahabiya, sailing north with the current from Aswan to Luxor. The pace is gentle but the highlights are complete — Philae, Kom Ombo, Edfu, and the great monuments of Thebes.",[37,40],{"label":38,"value":39},"Pace","Express · relaxed",{"label":41,"value":42},"Dining","Local & international",[44],{"label":14,"from":45,"to":46,"insights":47,"timeline":48},"Aswan","Luxor",[],[49,75,99,117],{"title":50,"places":51,"description":52,"image":34,"schedule":53},"Aswan → Kom Ombo",[27],"Embark aboard your elegant dahabiya and settle into the calm of the Nile. After lunch on board, a guided visit to the enchanting Philae Temple on Agilkia Island, dedicated to Isis. Begin sailing toward Kom Ombo with the silence of traditional navigation — no engine, only water and breeze — and moor beneath a starlit sky.",[54,57,60,63,66,69,72],{"time":55,"text":56},"12:00","Embarkation aboard your dahabiya",{"time":58,"text":59},"12:00–13:00","Lunch on board — local & international cuisine",{"time":61,"text":62},"13:00–17:00","Guided visit to Philae Temple, Agilkia Island",{"time":64,"text":65},"17:00","Sunset afternoon tea on deck",{"time":67,"text":68},"18:00","Begin sailing toward Kom Ombo",{"time":70,"text":71},"19:00–20:00","Dinner on board",{"time":73,"text":74},"Overnight","Moored near Kom Ombo",{"title":76,"places":77,"description":79,"image":80,"schedule":81},"Kom Ombo → Edfu → Luxor",[28,78],"Edfu Temple","Wake to sunrise views before visiting the unique Kom Ombo Temple, dedicated to Sobek and Horus. Sail on past palm groves and villages to Edfu, home to the best-preserved temple in Egypt, then continue toward Luxor via Esna with long, relaxed hours on deck.","/images/egypte-veda-248-van-577-2-1280x800.jpg",[82,85,88,91,94,97],{"time":83,"text":84},"06:00–07:00","Breakfast with sunrise views",{"time":86,"text":87},"07:00–08:00","Visit Kom Ombo Temple",{"time":89,"text":90},"08:00","Sail toward Edfu",{"time":92,"text":93},"13:00–15:00","Explore the Temple of Edfu",{"time":95,"text":96},"15:00","Continue sailing to Luxor via Esna",{"time":73,"text":98},"Arrival and overnight in Luxor",{"title":100,"places":101,"description":103,"image":104,"schedule":105},"Luxor — West & East Banks",[30,102,32],"Karnak Temple","An early start for Luxor's West Bank and the Valley of the Kings, where pharaohs were laid to rest in painted rock-cut tombs. In the afternoon, the vast Karnak Temple complex and the elegant Luxor Temple on the Nile Corniche, luminous as the day softens.","/images/karnak-1280x800.jpg",[106,109,112,114,115],{"time":107,"text":108},"05:00–05:30","Early breakfast",{"time":110,"text":111},"05:30–12:00","West Bank — Valley of the Kings",{"time":61,"text":113},"Karnak Temple, then Luxor Temple",{"time":64,"text":65},{"time":73,"text":116},"Moored in Luxor",{"title":118,"places":119,"description":120,"image":121,"schedule":122},"Disembarkation",[46],"After breakfast on board, check out and disembark in Luxor, concluding your tranquil sailing experience.","/images/more_than_plan.jpg",[123,125],{"time":83,"text":124},"Breakfast on board",{"time":89,"text":126},"Check-out & disembarkation",[128,131,134],{"q":129,"a":130},"Is this itinerary too short to see the highlights?","Not at all — three nights covers the Nile's essential temples: Philae, Kom Ombo, Edfu, and the great monuments of Luxor. It is ideal for travellers with limited time who still want the full dahabiya experience.",{"q":132,"a":133},"What is included on board?","Your cabin, all meals featuring local and international cuisine, the daily sunset afternoon tea on deck, and the crew are included. Temple entrance fees, guides, and transfers are arranged for you and quoted with your charter.",{"q":135,"a":136},"Can we sail from Luxor to Aswan instead?","Yes. The same highlights can be arranged in the reverse direction to suit your arrival city — just let us know and we will tailor it.",[],[],false,"src/content/itineraries/3n-4d-aswan-luxor.json","e1c5becb3101db64","6n-7d-aswan-dendera-luxor",{"id":142,"data":144,"filePath":378,"digest":379},{"title":145,"summary":146,"description":147,"nights":148,"days":149,"experience":150,"series":151,"vessels":152,"highlights":153,"hero":33,"cardImage":156,"routeOverview":157,"facts":158,"routes":164,"faq":359,"tips":372,"insights":373,"featured":377,"comingSoon":139,"draft":139},"Aswan ⇄ Dendera ⇄ Luxor","Our signature \"Long Cruise\" — the classic southern route deepened with an exclusive excursion to Abydos and the magnificent Temple of Dendera.","A deep exploration of the Nile, combining the classic temples of the south with a rare pilgrimage to Abydos and Dendera — two of Egypt's most sacred and least-visited cult centres, often missed on standard itineraries. The schedule balances iconic sights with serene sailing.",6,7,"Dendera & Abydos","aswan-dendera-luxor",[22,23,24,25],[27,28,29,154,155,31],"Abydos","Dendera","/images/Dendera_temple2.jpg","Six nights threading the Nile's great temples, with an exclusive full day ashore at Abydos and Dendera. Sailable in either direction — beginning amid the islands of Aswan, or with the grandeur of Thebes — both reaching the sublime reliefs of the Temple of Seti I and Dendera's painted astronomical ceiling.",[159,162],{"label":160,"value":161},"Temples","9+ major sites",{"label":38,"value":163},"Relaxed · flexible",[165,270],{"label":166,"from":45,"to":46,"tagline":167,"overview":168,"insights":169,"timeline":170},"Aswan → Dendera → Luxor","Journey Through the Ages","This 6-night \"Long Cruise\" offers a deep exploration of the Nile, combining the classic southern route with an exclusive excursion to the magnificent Temple of Dendara. The schedule is designed to make the most of each day, balancing iconic sights with serene sailing.",[],[171,185,209,222,237,254,263],{"title":172,"places":173,"description":174,"image":175,"schedule":176},"Embarkation & The Goddess Isis's Sanctuary",[27],"Arrive in Aswan and step aboard — your journey begins on the island of Isis.","/images/philae_temple.jpg",[177,180,183],{"time":178,"text":179},"Afternoon","Arrive in Aswan, board your dahabiya, and settle in.",{"time":181,"text":182},"Late afternoon","Visit the beautiful Philae Temple — a motorboat to Agilkia Island reveals this Graeco-Roman complex dedicated to Isis, famed for its elegant columns and picturesque setting.",{"time":73,"text":184},"Docked in Aswan.",{"title":186,"places":187,"description":189,"image":190,"schedule":191},"The Dual Temple & Ancient Sandstone Quarries",[28,188],"Gebel el-Silsila","Two great riverside monuments, with serene sailing in between.","/images/The_Dual_Temple_of_Sobek&Haroeris.jpg",[192,195,198,201,204,207],{"time":193,"text":194},"6:00 AM","Set sail north towards Kom Ombo.",{"time":196,"text":197},"9:00 AM","Visit the unique Temple of Kom Ombo, dedicated to two gods — the crocodile-headed Sobek and the falcon-headed Horus.",{"time":199,"text":200},"10:00 AM","Continue sailing to the historic site of El Silsila.",{"time":202,"text":203},"2:00 PM","Explore the El Silsila quarries — the source of sandstone for Egypt's great temples — with cliff-side chapels and royal stelae carved into the rock.",{"time":205,"text":206},"3:00 PM","Sail onwards to Edfu.",{"time":73,"text":208},"Docked in Edfu.",{"title":210,"places":211,"description":212,"image":213,"schedule":214},"The Falcon God's Citadel & Sailing to Thebes",[78],"Egypt's best-preserved temple, then a full day on the water.","/images/horus_temple.jpg",[215,218,220],{"time":216,"text":217},"8:00 AM","Visit the remarkably preserved Temple of Edfu, the largest dedicated to the god Horus — its massive pylon, courtyards, and intact inner halls a highlight of Ptolemaic architecture.",{"time":199,"text":219},"Depart Edfu for a full day of scenic sailing towards Luxor, ancient Thebes.",{"time":73,"text":221},"Docked in Luxor.",{"title":223,"places":224,"description":227,"image":228,"schedule":229},"Theban Necropolis & Voyage to the Goddess Hathor",[30,225,226],"Temple of Hatshepsut","Colossi of Memnon","The West Bank of Thebes, then a special sail north toward Dendara.","/images/Temple_of_Hatshepsut.jpg",[230,232,235],{"time":193,"text":231},"Cross the Nile to the West Bank — the Valley of the Kings, the Temple of Hatshepsut at Deir el-Bahari, and the towering Colossi of Memnon.",{"time":233,"text":234},"1:00 PM","A special northward sail to the city of Qena, the docking point for Dendara.",{"time":73,"text":236},"Docked near Dendara.",{"title":238,"places":239,"description":242,"image":243,"schedule":244},"Pilgrimage to Abydos & The Temple of Hathor",[154,240,241],"Temple of Seti I","Dendera Temple","A full day ashore at two of Egypt's most sacred, least-visited temples.","/images/Temple_of_Seti.jpg",[245,248,250,253],{"time":246,"text":247},"Full day · by road","Travel to Abydos — the magnificent Temple of Seti I, with its exquisite raised reliefs and the mystical Abydos King List, and the nearby Osireion.",{"time":178,"text":249},"Return to Qena for the stunning Temple of Dendara, dedicated to Hathor — its famous astronomical ceiling, vivid column capitals, and rooftop chapels.",{"time":251,"text":252},"Evening","Set sail back to Luxor.",{"time":73,"text":221},{"title":255,"places":256,"description":257,"image":104,"schedule":258},"The Grand Temples of Thebes",[102,32],"The grand finale, on the East Bank of ancient Thebes.",[259,262],{"time":260,"text":261},"Full day","Stand within the colossal Karnak Temple Complex — the forest of pillars in the Great Hypostyle Hall — then the elegant Luxor Temple on the Nile Corniche.",{"time":73,"text":221},{"title":118,"places":264,"description":265,"image":121,"schedule":266},[46],"Farewell to the river.",[267],{"time":268,"text":269},"Morning","After breakfast, disembark in Luxor, concluding your deep journey through Egyptian history and spirituality.",{"label":271,"from":46,"to":45,"tagline":272,"overview":273,"insights":274,"timeline":278},"Luxor → Dendera → Aswan","Sacred Journey South","This six-night itinerary offers a strategic and enriching route. First explore the wonders of ancient Thebes (Luxor), then embark on a special excursion north to the cult temples of Abydos and Dendara, before a relaxing downriver sail to Aswan — concluding with the beautiful sites of the south.",[275,276,277],"Strategic route — this direction lets you experience the grandeur of Luxor first, when energy is highest, followed by the special excursion. The upriver sail from Luxor to Aswan can allow for a more relaxed pace.","Abydos & Dendera — the Day 3 excursion is a significant full-day road trip from Qena, requiring an early start, but is uniquely rewarding for those drawn to deep historical and religious sites.","Aswan as a finale — ending in Aswan offers a natural conclusion, with the option to extend your stay toward the temples of Abu Simbel, a highlight of any southern Egypt itinerary.",[279,289,296,307,319,339,352],{"title":280,"places":281,"description":282,"image":104,"schedule":283},"Embarkation in Thebes & The East Bank",[102,32],"Board in Luxor and begin amid the grandeur of ancient Thebes.",[284,286,288],{"time":178,"text":285},"Arrive and board your dahabiya in Luxor.",{"time":251,"text":287},"Explore the East Bank — the colossal Karnak Temple Complex, a city of temples, obelisks, and the forest of 134 columns in the Great Hypostyle Hall — then the graceful Luxor Temple, illuminated at dusk.",{"time":73,"text":221},{"title":290,"places":291,"description":292,"image":228,"schedule":293},"The Theban West Bank",[30,225,226],"The necropolis of ancient Thebes, before the special excursion north.",[294,295],{"time":268,"text":231},{"time":73,"text":221},{"title":238,"places":297,"description":298,"image":243,"schedule":299},[154,240,241],"A full day ashore at two of Egypt's most significant temples.",[300,302,304,306],{"time":246,"text":301},"Travel to Abydos — the magnificent Temple of Seti I, with its exquisite raised reliefs and the mystical Abydos King List.",{"time":178,"text":303},"Return to the Qena area for the stunning Temple of Dendara, dedicated to Hathor — its vividly painted astronomical ceiling, crypts, and iconic Hathor-headed columns.",{"time":251,"text":305},"Sail back south from Qena to Luxor.",{"time":73,"text":221},{"title":308,"places":309,"description":311,"image":312,"schedule":313},"Sailing South via Esna to Edfu",[310],"Esna Lock","A full day of relaxed sailing after the intensive temple days.","/images/Esna_lock.jpg",[314,317],{"time":315,"text":316},"Day","Sail downriver towards Edfu, passing through the Esna Lock — a feat of modern engineering that regulates the river's flow — as rural Egyptian life unfolds along the banks.",{"time":73,"text":318},"Docked near Edfu.",{"title":320,"places":321,"description":322,"image":213,"schedule":323},"Edfu, El Silsila & Kom Ombo",[78,188,28],"Three monuments and a final serene sail to Aswan.",[324,327,329,331,333,336,338],{"time":325,"text":326},"7:00 AM","Visit the monumental Temple of Edfu, dedicated to the falcon god Horus.",{"time":196,"text":328},"Sail south from Edfu to El Silsila.",{"time":233,"text":330},"Explore the sandstone quarries of El Silsila — the cliff-side Speos of Horemheb and royal stelae carved into the rock faces.",{"time":202,"text":332},"Sail onwards to Kom Ombo.",{"time":334,"text":335},"4:00 PM","Visit the unique Temple of Kom Ombo, dedicated to both Sobek and Horus — its riverside setting beautiful in the late-afternoon light.",{"time":251,"text":337},"A final serene sail to Aswan.",{"time":73,"text":184},{"title":340,"places":341,"description":345,"image":175,"schedule":346},"The Island of Isis",[27,342,343,344],"High Dam","Old Dam","Unfinished Obelisk","Aswan's sacred island and its modern marvels.",[347,349,351],{"time":268,"text":348},"Visit the beautiful Philae Temple — a short motorboat ride to Agilkia Island reveals this Graeco-Roman complex dedicated to Isis, famed for its elegant pillars.",{"time":178,"text":350},"On the way back, see Aswan's High Dam, the Old Dam, and the Unfinished Obelisk.",{"time":73,"text":184},{"title":353,"places":354,"description":355,"image":121,"schedule":356},"Disembarkation in Aswan",[45],"Farewell to the river — with Abu Simbel within reach.",[357],{"time":268,"text":358},"After breakfast, disembark in Aswan — with the option to extend your stay toward the temples of Abu Simbel.",[360,363,366,369],{"q":361,"a":362},"What makes this the \"Long Cruise\"?","The inclusion of Abydos makes this uniquely comprehensive, offering access to one of Egypt's most sacred and historically significant sites — the Temple of Seti I — alongside Dendera, both often missed on standard itineraries.",{"q":364,"a":365},"How demanding is the Abydos & Dendera day?","It is a full-day road excursion from Qena (roughly 1.5 hours each way to Abydos) requiring an early start, but it is uniquely rewarding for travellers drawn to deep historical and spiritual sites. Comfortable shoes, sun protection, and water are essential.",{"q":367,"a":368},"Which direction will we sail?","Either Aswan to Luxor or Luxor to Aswan — the temples are the same, the order differs. Starting in Luxor lets you experience the grandeur of Thebes first; ending in Aswan opens the option to extend toward Abu Simbel. We tailor the direction to your travel plans.",{"q":370,"a":371},"Can the order of visits change?","Yes. This is a private, flexible charter and a general framework — your guide may adjust the sequence of visits, especially on the West Bank, to ensure the best experience based on river, lock, and site conditions.",[],[374,375,376],"Day 5 — Abydos & Dendera is a full-day road excursion (about 1.5 hours each way from Qena to Abydos), requiring an early start. The day-by-day reflects a realistic timeline for this exceptional day of sightseeing.","The inclusion of Abydos makes this a uniquely comprehensive \"Long Cruise,\" offering access to one of Egypt's most sacred and historically significant sites — often missed on standard itineraries.","The sequence of visits, especially on the West Bank, may be arranged by your guide to ensure the best possible experience based on conditions.",true,"src/content/itineraries/6n-7d-aswan-dendera-luxor.json","2016a95b548bb11d","13n-14d-cairo-aswan",{"id":380,"data":382,"filePath":710,"digest":711},{"title":383,"summary":384,"description":385,"nights":386,"days":387,"experience":388,"series":389,"vessels":390,"highlights":391,"hero":33,"cardImage":394,"routeOverview":395,"facts":396,"routes":402,"faq":696,"tips":706,"insights":707,"featured":139,"comingSoon":139,"draft":139},"Cairo ⇄ Aswan","The entire length of the Nile — thirteen nights linking the Pyramids of Giza with the temples of Aswan, the most complete dahabiya voyage we offer.","Discover the whole river aboard a traditional dahabiya, towed for the long northern reaches and sailing the classic south. From Giza and the Fayoum through Middle Egypt's hidden tombs to Abydos, Dendera, Thebes, Edfu, Kom Ombo, and Aswan — daily international buffet dining and the signature sunset tea on deck throughout.",13,14,"Grand Journey","cairo-aswan",[22,23,24,25],[392,393,154,155,30,27],"Giza Pyramids","Tell el-Amarna","/images/nubian-village.jpg","Thirteen nights from the Mediterranean delta to the Nubian south — Giza, Fayoum, Tell el-Amarna and Beni Hassan, Abydos and Dendera, the monuments of Luxor, then Edfu, Kom Ombo, and the island temple of Philae at Aswan. Sailable Cairo → Aswan (southbound, against the current) or Aswan → Cairo (northbound, with the current).",[397,400],{"label":398,"value":399},"Vessel","Dahabiya under tow",{"label":41,"value":401},"Daily buffet · sunset tea",[403,572],{"label":404,"from":405,"to":45,"tagline":406,"overview":407,"insights":408,"timeline":409},"Cairo → Aswan","Cairo","Upstream to Nubia","Sailing southbound against the Nile current aboard a towed dahabiya, this direction builds gradually from the Pyramids of Giza through Middle Egypt toward the great temples of the south, ending amid the islands of Aswan.",[],[410,423,436,448,461,475,487,498,509,521,533,542,556,566],{"title":411,"places":412,"description":413,"image":414,"schedule":415},"Arrival in Cairo",[405],"Arrive in Cairo at the start of the river.","/images/egypte-veda-214-van-577-2000x709.jpg",[416,419,421],{"time":417,"text":418},"On arrival","Transfer to your hotel or directly to your dahabiya for embarkation.",{"time":251,"text":420},"Welcome dinner on board.",{"time":73,"text":422},"Cairo.",{"title":424,"places":425,"description":427,"image":428,"schedule":429},"Cairo Sightseeing",[392,426],"Egyptian Museum","The Pyramids of Giza and the Egyptian Museum.","/images/pyramids_of_Giza.jpg",[430,432,435],{"time":315,"text":431},"Explore the legendary Pyramids of Giza and the treasures of the Egyptian Museum.",{"time":433,"text":434},"Meals","All meals on board, including sunset tea with snacks.",{"time":73,"text":422},{"title":437,"places":438,"description":440,"image":441,"schedule":442},"Sail to Beni Suef",[439],"Beni Suef","The first long sail south through Middle Egypt.","/images/top_river2.jpg",[443,446],{"time":444,"text":445},"Sailing","South to Beni Suef — approx. 120 km · 17–18 hrs against the current.",{"time":73,"text":447},"Beni Suef.",{"title":449,"places":450,"description":453,"image":121,"schedule":454},"Fayoum Excursion",[451,452],"Hawara Pyramid","Meidum Pyramid","Two of Egypt's earliest pyramids.",[455,458,460],{"time":456,"text":457},"Excursion","The ancient Hawara and Meidum pyramids.",{"time":251,"text":459},"Sunset tea and dinner on board.",{"time":73,"text":447},{"title":462,"places":463,"description":466,"image":33,"schedule":467},"Sail to Minya — Tuna el-Gebel & Ashmunein",[464,465],"Tuna el-Gebel","Ashmunein","South to Minya, with two Middle-Egypt sites.",[468,470,473],{"time":444,"text":469},"On to Minya — approx. 145 km · 20–21 hrs against the current.",{"time":471,"text":472},"Visit","Tuna el-Gebel and Ashmunein.",{"time":73,"text":474},"Minya.",{"title":476,"places":477,"description":479,"image":480,"schedule":481},"Tell el-Amarna & Beni Hassan",[393,478],"Beni Hassan","The painted tombs of Middle Egypt.","/images/aswan-temples-1280x800.jpg",[482,484,486],{"time":268,"text":483},"Tell el-Amarna — the Northern Tombs and the Tomb of Ahmose (EA3).",{"time":178,"text":485},"The remarkable tombs of Beni Hassan.",{"time":73,"text":474},{"title":488,"places":489,"description":492,"image":441,"schedule":493},"Sail to Sohag via Asyut",[490,491],"Sohag","Asyut","A long day sailing south through Upper Egypt.",[494,496],{"time":444,"text":495},"South to Sohag via Asyut — approx. 225 km · 31–33 hrs against the current.",{"time":73,"text":497},"Sohag.",{"title":499,"places":500,"description":501,"image":243,"schedule":502},"Abydos — Sail to Qena",[154,240],"The sacred city of Osiris, then onward south.",[503,505,507],{"time":268,"text":504},"Excursion to the magnificent Temple of Abydos.",{"time":444,"text":506},"South toward Qena — approx. 160 km · 22–23 hrs against the current.",{"time":73,"text":508},"Qena.",{"title":510,"places":511,"description":512,"image":513,"schedule":514},"Dendera Temple — Sail to Luxor",[241],"The Temple of Hathor, then on to Thebes.","/images/Dendera_temple.jpg",[515,517,519],{"time":268,"text":516},"Visit the beautifully preserved Temple of Dendara.",{"time":444,"text":518},"On to Luxor — approx. 65 km · 9–10 hrs against the current.",{"time":73,"text":520},"Luxor.",{"title":522,"places":523,"description":524,"image":104,"schedule":525},"Luxor Sightseeing",[30,225,102,32],"The wonders of ancient Thebes, both banks.",[526,529,532],{"time":527,"text":528},"West Bank","The Valley of the Kings and the mortuary Temple of Hatshepsut.",{"time":530,"text":531},"East Bank","The Karnak Temple complex and Luxor Temple.",{"time":73,"text":520},{"title":534,"places":535,"description":536,"image":441,"schedule":537},"Sail to Edfu",[29],"Continue south toward Edfu.",[538,540],{"time":444,"text":539},"South to Edfu — approx. 110 km · 15–17 hrs against the current.",{"time":73,"text":541},"Edfu.",{"title":543,"places":544,"description":545,"image":546,"schedule":547},"Edfu Temple — Sail to Kom Ombo & Aswan",[78,28],"Two southern temples, then on to Aswan.","/images/edfu_temple.jpg",[548,550,552,554],{"time":268,"text":549},"Visit the impressive Temple of Edfu.",{"time":178,"text":551},"Sail to Kom Ombo for its unique double temple.",{"time":444,"text":553},"On to Aswan — approx. 105 km · 14–15 hrs against the current.",{"time":73,"text":555},"Farewell dinner on board · Aswan.",{"title":557,"places":558,"description":560,"image":175,"schedule":561},"Aswan Sightseeing",[342,27,559],"Nubian Museum","The treasures of the south.",[562,564],{"time":315,"text":563},"The remarkable Aswan High Dam, the island Temple of Philae, and the fascinating Nubian Museum.",{"time":73,"text":565},"Aswan.",{"title":567,"places":568,"description":265,"image":121,"schedule":569},"Disembarkation & Departure",[45],[570],{"time":268,"text":571},"Disembark and transfer to Aswan Airport for your onward flight home.",{"label":573,"from":45,"to":405,"tagline":574,"overview":575,"insights":576,"timeline":577},"Aswan → Cairo","Downstream to the Delta","Fly south to begin at Aswan, then sail home northbound with the Nile current — past the southern temples, the monuments of Thebes, and Middle Egypt's hidden tombs, ending at the Pyramids of Giza.",[],[578,585,595,601,611,621,628,639,647,656,665,675,685,691],{"title":411,"places":579,"description":580,"image":33,"schedule":581},[405],"Arrive in Cairo and overnight before flying south.",[582,584],{"time":417,"text":583},"Transfer to your hotel.",{"time":73,"text":422},{"title":586,"places":587,"description":588,"image":414,"schedule":589},"Fly to Aswan & Embarkation",[45],"Fly south to begin the river journey at Aswan.",[590,592,594],{"time":268,"text":591},"Flight to Aswan.",{"time":417,"text":593},"Embark your dahabiya.",{"time":73,"text":565},{"title":557,"places":596,"description":560,"image":175,"schedule":597},[342,27,559],[598,600],{"time":315,"text":599},"The High Dam, the island Temple of Philae, and the Nubian Museum.",{"time":73,"text":565},{"title":602,"places":603,"description":604,"image":190,"schedule":605},"Sail to Kom Ombo & Edfu",[28,29],"North to two southern temples.",[606,608,610],{"time":471,"text":607},"Kom Ombo and its unique double temple, dedicated to Sobek and Horus.",{"time":444,"text":609},"On to Edfu — approx. 105 km · 12–13 hrs with partial current assistance.",{"time":73,"text":541},{"title":612,"places":613,"description":614,"image":546,"schedule":615},"Edfu Temple — Sail to Luxor",[78],"The temple of Horus, then on to Thebes.",[616,618,620],{"time":268,"text":617},"Visit the Temple of Edfu.",{"time":444,"text":619},"On to Luxor — approx. 110 km · 13–14 hrs.",{"time":73,"text":520},{"title":522,"places":622,"description":524,"image":104,"schedule":623},[30,225,102,32],[624,626,627],{"time":527,"text":625},"The Valley of the Kings and the Temple of Hatshepsut.",{"time":530,"text":531},{"time":73,"text":520},{"title":629,"places":630,"description":631,"image":243,"schedule":632},"Sail to Qena — Abydos & Dendera",[154,241],"North to two sacred cult temples.",[633,636,638],{"time":634,"text":635},"Excursions","The temples of Abydos and Dendara.",{"time":444,"text":637},"North to Qena — approx. 65 km · 7½–8 hrs with the current.",{"time":73,"text":508},{"title":640,"places":641,"description":642,"image":441,"schedule":643},"Sail to Sohag via Naga Hammadi",[490],"A full sailing day north.",[644,646],{"time":444,"text":645},"North past the Naga Hammadi barrage to Sohag — approx. 160 km · 18–19 hrs with the current.",{"time":73,"text":497},{"title":648,"places":649,"description":651,"image":441,"schedule":652},"Sail to Minya",[650],"Minya","A full day sailing north along the valley.",[653,655],{"time":444,"text":654},"North to Minya — approx. 225 km · 26–28 hrs with the current.",{"time":73,"text":474},{"title":657,"places":658,"description":659,"image":480,"schedule":660},"Tell el-Amarna, Tuna el-Gebel & Ashmunein",[393,464,465],"A day among Middle Egypt's monuments.",[661,663,664],{"time":268,"text":662},"Tell el-Amarna and its Northern Tombs, including the Tomb of Ahmose.",{"time":178,"text":472},{"time":73,"text":474},{"title":666,"places":667,"description":668,"image":33,"schedule":669},"Beni Hassan — Sail to Beni Suef",[478],"The rock-cut tombs, then north.",[670,672,674],{"time":268,"text":671},"The rock-cut tombs of Beni Hassan.",{"time":444,"text":673},"North to Beni Suef — approx. 145 km · 16–18 hrs with the current.",{"time":73,"text":447},{"title":676,"places":677,"description":678,"image":121,"schedule":679},"Fayoum Excursion — Sail to Cairo",[451,452],"Egypt's earliest pyramids, then the capital.",[680,682,684],{"time":456,"text":681},"The Hawara and Meidum pyramids.",{"time":444,"text":683},"On to Cairo — approx. 120 km · 14–15 hrs with the current.",{"time":73,"text":422},{"title":424,"places":686,"description":427,"image":428,"schedule":687},[392,426],[688,690],{"time":315,"text":689},"Tour the Pyramids of Giza and the Egyptian Museum.",{"time":73,"text":422},{"title":567,"places":692,"description":265,"image":121,"schedule":693},[405],[694],{"time":268,"text":695},"Transfer to the airport for your onward international flight.",[697,700,703],{"q":698,"a":699},"Is this the most complete Nile itinerary?","Yes — thirteen nights covers the entire navigable Nile between Cairo and Aswan, combining Middle Egypt's rarely-seen monuments with the classic temples of the south, all aboard a single traditional dahabiya.",{"q":701,"a":702},"How does the towing work, and why?","For the long northern reaches a support tugboat tows the dahabiya, allowing an authentic, leisurely cruise over distances no sailing dahabiya could cover alone. Southbound (Cairo → Aswan) runs against the current and is around 15–20% slower than the northbound direction.",{"q":704,"a":705},"Which direction should we choose?","Both visit the same sites. Cairo → Aswan builds gradually toward the southern temples; Aswan → Cairo flies you south to begin and sails home with the current. We tailor the direction to your flights and preferences.",[],[708,709],"This is a traditional dahabiya towed by a support tugboat for the long northern reaches — sailing times are far longer than conventional cruisers, for an authentic, leisurely passage.","Thirteen nights covers the entire navigable Nile, combining Middle Egypt's rarely-seen monuments with the classic temples of the south aboard a single vessel.","src/content/itineraries/13n-14d-cairo-aswan.json","d65a0d1c2f72364d","7n-8d-aswan-dendera-luxor",{"id":712,"data":714,"filePath":741,"digest":742},{"title":145,"summary":715,"nights":149,"days":716,"experience":150,"series":151,"vessels":717,"highlights":718,"hero":33,"cardImage":513,"routeOverview":719,"facts":720,"routes":723,"faq":738,"tips":739,"insights":740,"featured":139,"comingSoon":139,"draft":139},"The extended \"Long Cruise\" — seven nights threading the southern temples with the exclusive pilgrimage to Abydos and Dendera, at the most generous pace.",8,[22,23,24,25],[27,28,29,154,155,31],"Seven nights combining the classic southern route with the special excursion to Abydos and Dendera — the same sacred itinerary as our six-night Long Cruise, with an extra day to savour it. Sailable in either direction.",[721],{"label":38,"value":722},"Extended · flexible",[724,732],{"label":166,"from":45,"to":46,"insights":725,"timeline":726},[],[727],{"title":728,"places":729,"description":730,"image":33,"schedule":731},"Detailed day-by-day coming soon",[],"We're finalising the full daily programme for this voyage. Contact us and we'll share the complete itinerary, tailored to your dates and group.",[],{"label":271,"from":46,"to":45,"insights":733,"timeline":734},[],[735],{"title":728,"places":736,"description":730,"image":33,"schedule":737},[],[],[],[],[],"src/content/itineraries/7n-8d-aswan-dendera-luxor.json","b8d7bff24c5e9a20","5n-6d-aswan-luxor",{"id":743,"data":745,"filePath":932,"digest":933},{"title":746,"summary":747,"description":748,"nights":749,"days":148,"experience":19,"series":20,"vessels":750,"highlights":751,"hero":33,"cardImage":753,"routeOverview":754,"facts":755,"routes":761,"faq":921,"tips":930,"insights":931,"featured":139,"comingSoon":139,"draft":139},"Aswan ⇄ Luxor","A classic five-night Nile voyage blending awe-inspiring temples with the tranquil rhythm of river life — sailable in either direction.","Journey through the heart of ancient Egypt between the engineering marvels of Aswan and the monumental wonders of Luxor. Five nights allow you to explore the major highlights at a relaxed pace, with the option of a breathtaking side trip to Abu Simbel.",5,[22,23,24,25],[27,28,29,752,30,31],"El Kab","/images/photo-2019-03-21-12.50.06-1280x854.jpg","The classic stretch of the Nile, sailed at a relaxed pace. Both directions visit the same great temples — Philae, Kom Ombo, Edfu, El Kab, and the monuments of Thebes — with the order tailored to your arrival city and an optional excursion to Abu Simbel.",[756,759],{"label":757,"value":758},"Abu Simbel","Optional excursion",{"label":38,"value":760},"Classic · relaxed",[762,844],{"label":14,"from":45,"to":46,"tagline":763,"overview":764,"insights":765,"timeline":766},"Upstream Through the Ages","Journey through the heart of ancient Egypt on a classic Nile voyage, blending awe-inspiring temple visits with the tranquil rhythm of river life — from the engineering marvels of Aswan to the monumental wonders of Luxor.",[],[767,779,799,813,826,839],{"title":768,"places":769,"description":770,"image":175,"schedule":771},"Aswan — Embarkation & City Highlights",[27,342,343,344],"Board in Aswan and explore the city's ancient and modern marvels.",[772,775,777],{"time":773,"text":774},"Arrival","Embark your dahabiya in Aswan and enjoy lunch on board.",{"time":178,"text":776},"Visit Philae Temple on Agilkia Island, the monumental High Dam that created Lake Nasser, the British-built Old Dam of 1902, and the Unfinished Obelisk in the granite quarries.",{"time":73,"text":778},"Dinner and your first night moored in Aswan.",{"title":780,"places":781,"description":784,"image":785,"schedule":786},"Abu Simbel Option & Sailing to Kom Ombo",[28,782,783],"Abu Simbel (optional)","Nubian Village","An optional dawn excursion, then north to the double temple.","/images/Abu_Simbel_Temple.jpg",[787,790,793,795,797],{"time":788,"text":789},"Morning · option A","An early excursion (by plane or convoy) to the colossal temples of Abu Simbel, built by Ramses II.",{"time":791,"text":792},"Morning · option B","A relaxed visit to Aswan's Botanical Gardens on Kitchener's Island and a traditional Nubian village.",{"time":178,"text":794},"Begin your cruise northward.",{"time":181,"text":796},"Disembark to explore the unique Temple of Kom Ombo, dedicated to Sobek and Horus.",{"time":73,"text":798},"Moored near Edfu.",{"title":800,"places":801,"description":802,"image":213,"schedule":803},"Edfu Temple & Onward to El Kab",[78,752],"Egypt's best-preserved temple, reached by horse-drawn carriage.",[804,806,809,811],{"time":268,"text":805},"Travel by horse-drawn carriage to the immensely well-preserved Temple of Edfu, dedicated to the falcon god Horus.",{"time":807,"text":808},"Midday","Cruise toward the ancient site of El Kab.",{"time":178,"text":810},"Enjoy the passing river scenery from the sundeck.",{"time":73,"text":812},"Moored near El Kab.",{"title":814,"places":815,"description":816,"image":312,"schedule":817},"El Kab & Sailing to Luxor via Esna",[752,310],"An ancient city, then through the Esna lock to Luxor.",[818,820,822,824],{"time":268,"text":819},"Explore the archaeological site of El Kab — an ancient city of tombs, temples, and rock inscriptions.",{"time":807,"text":821},"Cruise toward Luxor, passing through the Esna Lock (observed from deck) and the town of Esna.",{"time":251,"text":823},"Arrive in Luxor.",{"time":73,"text":825},"Moored in Luxor.",{"title":827,"places":828,"description":829,"image":228,"schedule":830},"Luxor — Thebes, City of the Gods",[30,225,226,102,32],"Both banks of ancient Thebes in a single, unforgettable day.",[831,834,837],{"time":832,"text":833},"Morning · West Bank","The Theban Necropolis — the Valley of the Kings, the Temple of Hatshepsut at Deir el-Bahari, and the Colossi of Memnon.",{"time":835,"text":836},"Afternoon · East Bank","The magnificent Karnak Temple complex and the elegant Luxor Temple, beautifully lit at dusk.",{"time":73,"text":838},"Farewell dinner and final night on board in Luxor.",{"title":118,"places":840,"description":265,"image":121,"schedule":841},[46],[842],{"time":268,"text":843},"After breakfast on board, disembark at your leisure in Luxor, marking the end of your Nile cruise.",{"label":845,"from":46,"to":45,"tagline":846,"overview":847,"insights":848,"timeline":849},"Luxor → Aswan","Downstream to Nubia","Sail south along the legendary Nile from the world's greatest open-air museum in Luxor to the graceful city of Aswan, exploring the major highlights at a relaxed pace — concluding with the option of a breathtaking side trip to Abu Simbel.",[],[850,861,872,887,903,916],{"title":851,"places":852,"description":853,"image":104,"schedule":854},"Luxor — Arrival & East Bank Wonders",[102,32],"Board in Luxor amid the grandeur of ancient Thebes.",[855,857,859],{"time":773,"text":856},"Board your dahabiya in Luxor and enjoy a welcome lunch.",{"time":178,"text":858},"Explore the East Bank — the vast Karnak Temple complex of pylons and obelisks, and the majestic Luxor Temple, illuminated after dusk.",{"time":73,"text":860},"Dinner and your first night moored in Luxor.",{"title":862,"places":863,"description":864,"image":228,"schedule":865},"Luxor's West Bank & Sailing South",[30,225,226,310],"The Theban necropolis, then south through the Esna lock.",[866,868,870],{"time":268,"text":867},"Cross to the West Bank necropolis — the Valley of the Kings, the terraced Temple of Hatshepsut, and the Colossi of Memnon.",{"time":178,"text":869},"Begin your cruise south, passing through the Esna Lock.",{"time":73,"text":871},"Moored near the ancient site of El Kab.",{"title":873,"places":874,"description":875,"image":213,"schedule":876},"El Kab & The Temple of Horus at Edfu",[752,78],"A pre-dynastic city and Egypt's best-preserved temple.",[877,879,881,883,885],{"time":268,"text":878},"Explore the ruins of El Kab, an important pre-dynastic and Pharaonic settlement.",{"time":807,"text":880},"Cruise to Edfu.",{"time":178,"text":882},"Travel by horse-drawn carriage to the magnificent Temple of Edfu, dedicated to the falcon god Horus.",{"time":251,"text":884},"Continue to the mooring at Gebel el-Silsila.",{"time":73,"text":886},"Moored near El Silsila.",{"title":888,"places":889,"description":890,"image":891,"schedule":892},"Gebel el-Silsila & Kom Ombo",[188,28],"Ancient quarries and the double temple, then on to Aswan.","/images/Gebel_El.jpg",[893,895,897,899,901],{"time":268,"text":894},"Discover Gebel el-Silsila — the ancient sandstone quarry with rock-cut shrines and royal stelae along the banks.",{"time":807,"text":896},"Cruise to Kom Ombo.",{"time":178,"text":898},"Tour the unique Temple of Kom Ombo, dedicated to both Sobek and Horus.",{"time":251,"text":900},"Enjoy the final stretch of sailing toward Aswan.",{"time":73,"text":902},"Moored in Aswan.",{"title":904,"places":905,"description":906,"image":175,"schedule":907},"Aswan's Treasures & Abu Simbel Option",[27,342,343,344,782],"A full day with two ways to experience the south.",[908,911,914],{"time":909,"text":910},"Option 1 · Aswan","Visit the sublime island Temple of Philae, the High Dam, the Old Dam, and the Unfinished Obelisk.",{"time":912,"text":913},"Option 2 · Abu Simbel","A very early excursion (by plane or convoy) to the colossal rock-cut temples of Abu Simbel, returning to Aswan's highlights in the afternoon.",{"time":73,"text":915},"Farewell dinner and final night on board in Aswan.",{"title":118,"places":917,"description":355,"image":121,"schedule":918},[45],[919],{"time":268,"text":920},"After breakfast on board, disembark at your leisure in Aswan, marking the end of your cruise.",[922,924,927],{"q":704,"a":923},"Both directions visit the same temples; only the order and the sailing flow differ. Sailing from Luxor to Aswan is upriver and can feel more relaxed, and ends near Abu Simbel for an optional extension. We tailor the direction to your arrival city.",{"q":925,"a":926},"Is Abu Simbel included?","Abu Simbel is offered as an optional excursion by plane or convoy on the Aswan day. We arrange it on request and quote it with your charter.",{"q":928,"a":929},"Are entrance fees and guides included?","The boat, all meals on board, and the crew are included. Temple entrance fees, expert guides, and land transfers are arranged for you and quoted with your private charter.",[],[],"src/content/itineraries/5n-6d-aswan-luxor.json","d39c6971e7dabb85","12n-13d-cairo-luxor",{"id":934,"data":936,"filePath":1202,"digest":1203},{"title":937,"summary":938,"description":939,"nights":940,"days":386,"experience":388,"series":941,"vessels":942,"highlights":943,"hero":33,"cardImage":428,"routeOverview":945,"facts":946,"routes":949,"faq":1188,"tips":1198,"insights":1199,"featured":139,"comingSoon":139,"draft":139},"Cairo ⇄ Luxor","The full sweep of the Nile aboard a traditional dahabiya under tow — from the Pyramids of Giza through Middle Egypt's hidden monuments to the temple cities of Thebes.","A rare twelve-night voyage along the river's least-travelled reaches, linking Cairo with Luxor. Traditional dahabiya cruising, gently towed by a support tugboat for the long passage, with daily international buffet dining and the signature sunset tea on deck.",12,"cairo-luxor",[22,23,24,25],[392,944,393,154,155,31],"Fayoum Pyramids","Twelve nights spanning Middle and Upper Egypt — the pyramids of Giza and Fayoum, the painted tombs of Tell el-Amarna and Beni Hassan, the sacred temples of Abydos and Dendera, and the grand monuments of Luxor. Sailable in either direction; northbound (Luxor → Cairo) runs with the current and is noticeably faster.",[947,948],{"label":398,"value":399},{"label":41,"value":401},[950,1071],{"label":951,"from":405,"to":46,"tagline":952,"overview":953,"insights":954,"timeline":955},"Cairo → Luxor","Upstream Through Egypt","Experience the timeless beauty of the Nile aboard a traditional dahabiya, elegantly towed by a support tugboat for long-distance navigation. Sailing southbound against the current, the days are unhurried — the point of this slow, authentic river journey.",[],[956,966,975,983,992,1000,1008,1018,1028,1038,1047,1055,1065],{"title":957,"places":958,"description":959,"image":960,"schedule":961},"Arrival in Cairo & Embarkation",[405],"Arrive in Cairo and step aboard at the start of the river.","/images/egypte-veda-381-van-577-2000x1250.jpg",[962,964,965],{"time":417,"text":963},"Transfer to your dahabiya for embarkation.",{"time":251,"text":420},{"time":73,"text":422},{"title":424,"places":967,"description":968,"image":428,"schedule":969},[392,426],"The Pyramids of Giza and the treasures of the Egyptian Museum.",[970,972,974],{"time":315,"text":971},"Visit the legendary Pyramids of Giza and the renowned Egyptian Museum.",{"time":433,"text":973},"All meals on board, including the daily sunset tea with snacks.",{"time":73,"text":422},{"title":976,"places":977,"description":440,"image":978,"schedule":979},"Sail from Cairo to Beni Suef",[439],"/images/Beni_Suef.jpg",[980,982],{"time":444,"text":981},"Cairo to Beni Suef — approx. 120 km · 16–18 hrs against the current, through the fertile landscapes of Middle Egypt.",{"time":73,"text":447},{"title":449,"places":984,"description":985,"image":986,"schedule":987},[451,452],"An excursion to two of Egypt's earliest pyramids.","/images/Meidum_Pyramid.jpg",[988,990,991],{"time":456,"text":989},"The ancient pyramids of Hawara and Meidum.",{"time":251,"text":459},{"time":73,"text":447},{"title":462,"places":993,"description":466,"image":994,"schedule":995},[464,465],"/images/Ashmunein.jpg",[996,998,999],{"time":444,"text":997},"On to Minya — approx. 145 km · 19–21 hrs against the current.",{"time":471,"text":472},{"time":73,"text":474},{"title":476,"places":1001,"description":479,"image":1002,"schedule":1003},[393,478],"/images/Beni_Hassan.jpg",[1004,1005,1007],{"time":268,"text":483},{"time":178,"text":1006},"The impressive rock-cut tombs of Beni Hassan.",{"time":73,"text":474},{"title":1009,"places":1010,"description":1011,"image":1012,"schedule":1013},"Sail to Asyut",[491],"A full sailing day toward Asyut.","/images/img-20180416-163539-947-676x450.jpg",[1014,1016],{"time":444,"text":1015},"On to Asyut — approx. 125 km · 17–18 hrs against the current, watching Middle Egypt drift by from the sundeck.",{"time":73,"text":1017},"Asyut.",{"title":1019,"places":1020,"description":1021,"image":243,"schedule":1022},"Sail to Sohag & Abydos",[154,240],"South to Sohag, with the sacred temple of Abydos.",[1023,1025,1027],{"time":444,"text":1024},"On to Sohag — approx. 100 km · 14–15 hrs against the current.",{"time":456,"text":1026},"The magnificent Temple of Abydos, dedicated to Osiris.",{"time":73,"text":497},{"title":1029,"places":1030,"description":1032,"image":1033,"schedule":1034},"Sail to Qena",[1031],"Qena","A leisurely sailing day toward Qena.","/images/egypte-veda-198-van-577-1280x800.jpg",[1035,1037],{"time":444,"text":1036},"On to Qena — approx. 160 km · 21–23 hrs against the current, panoramic Nile scenery from the sundeck.",{"time":73,"text":508},{"title":1039,"places":1040,"description":1041,"image":513,"schedule":1042},"Dendera Temple & Sail to Luxor",[241],"The Temple of Dendara, then on to Thebes.",[1043,1045,1046],{"time":268,"text":1044},"Visit the beautifully preserved Temple of Dendara, dedicated to Hathor.",{"time":444,"text":518},{"time":73,"text":520},{"title":1048,"places":1049,"description":1050,"image":228,"schedule":1051},"Valley of the Kings & Hatshepsut",[30,225],"The West Bank of ancient Thebes.",[1052,1054],{"time":315,"text":1053},"The Valley of the Kings and the spectacular mortuary Temple of Hatshepsut at Deir el-Bahari.",{"time":73,"text":520},{"title":1056,"places":1057,"description":1058,"image":104,"schedule":1059},"Karnak & Luxor Temples — Disembarkation",[102,32],"The grand temples of the East Bank, then farewell.",[1060,1062,1064],{"time":315,"text":1061},"The monumental Karnak Temple complex and the elegant Luxor Temple.",{"time":251,"text":1063},"Farewell dinner on board.",{"time":73,"text":520},{"title":1066,"places":1067,"description":1068,"image":121,"schedule":1069},"Departure",[46],"Disembarkation.",[1070],{"time":268,"text":695},{"label":1072,"from":46,"to":405,"tagline":574,"overview":1073,"insights":1074,"timeline":1075},"Luxor → Cairo","Sailing northbound from Luxor to Cairo with the Nile current, this direction runs roughly 15–20% faster than the southbound route — beginning amid the grandeur of Thebes and ending at the Pyramids of Giza.",[],[1076,1085,1094,1104,1113,1123,1131,1138,1148,1155,1164,1171,1184],{"title":1077,"places":1078,"description":1079,"image":1080,"schedule":1081},"Arrival in Luxor & Embarkation",[46],"Arrive in Luxor and step aboard amid ancient Thebes.","/images/dsc-1612-1-1280x800.jpg",[1082,1083,1084],{"time":417,"text":963},{"time":251,"text":420},{"time":73,"text":520},{"title":1048,"places":1086,"description":1087,"image":228,"schedule":1088},[30,225],"The West Bank necropolis of Thebes.",[1089,1091,1093],{"time":315,"text":1090},"The Valley of the Kings and the spectacular mortuary Temple of Hatshepsut.",{"time":433,"text":1092},"All meals on board, including sunset tea.",{"time":73,"text":520},{"title":1095,"places":1096,"description":1097,"image":104,"schedule":1098},"Karnak & Luxor Temples — Sail to Qena",[102,32],"The great temples of Thebes, then the journey north begins.",[1099,1101,1103],{"time":268,"text":1100},"The monumental Karnak Temple complex and Luxor Temple.",{"time":444,"text":1102},"North to Qena — approx. 65 km · 7–8 hrs with the current.",{"time":73,"text":508},{"title":1105,"places":1106,"description":1107,"image":513,"schedule":1108},"Dendera Temple — Sail toward Sohag",[241],"The Temple of Hathor, then onward north.",[1109,1110,1112],{"time":268,"text":516},{"time":444,"text":1111},"Toward Sohag — approx. 160 km · 17–19 hrs with the current.",{"time":73,"text":497},{"title":1114,"places":1115,"description":1116,"image":243,"schedule":1117},"Abydos — Sail to Asyut",[154,240],"The sacred city of Osiris, then sailing on.",[1118,1120,1122],{"time":456,"text":1119},"The magnificent Temple of Abydos.",{"time":444,"text":1121},"Toward Asyut — approx. 100 km · 11–12 hrs with the current.",{"time":73,"text":1017},{"title":648,"places":1124,"description":1125,"image":1126,"schedule":1127},[650],"A full, leisurely day sailing north.","/images/egypte-veda-311-van-577-1060x663.jpg",[1128,1130],{"time":444,"text":1129},"North through Middle Egypt to Minya — approx. 125 km · 14–15 hrs with the current.",{"time":73,"text":474},{"title":476,"places":1132,"description":479,"image":1002,"schedule":1133},[393,478],[1134,1135,1137],{"time":268,"text":483},{"time":178,"text":1136},"The tombs of Beni Hassan.",{"time":73,"text":474},{"title":1139,"places":1140,"description":1141,"image":1142,"schedule":1143},"Tuna el-Gebel & Ashmunein — Sail to Beni Suef",[464,465],"Two more Middle-Egypt sites, then north.","/images/Tuna_el-Gebel.jpg",[1144,1145,1147],{"time":471,"text":472},{"time":444,"text":1146},"Toward Beni Suef — approx. 145 km · 16–17 hrs with the current.",{"time":73,"text":447},{"title":449,"places":1149,"description":1150,"image":986,"schedule":1151},[451,452],"Egypt's earliest pyramids.",[1152,1153,1154],{"time":456,"text":989},{"time":251,"text":459},{"time":73,"text":447},{"title":1156,"places":1157,"description":1158,"image":1159,"schedule":1160},"Sail from Beni Suef to Cairo",[405],"The final sail to the capital.","/images/hero_1.jpg",[1161,1163],{"time":444,"text":1162},"North to Cairo — approx. 120 km · 13–15 hrs with the current, through the fertile landscapes of Middle Egypt.",{"time":73,"text":422},{"title":424,"places":1165,"description":427,"image":428,"schedule":1166},[392,426],[1167,1169,1170],{"time":315,"text":1168},"Visit the Pyramids of Giza and the renowned Egyptian Museum.",{"time":433,"text":1092},{"time":73,"text":422},{"title":1172,"places":1173,"description":1176,"image":1177,"schedule":1178},"Old Cairo & Disembarkation Preparations",[1174,1175],"Old Cairo","Khan el-Khalili","Optional exploration of historic Cairo.","/images/Khan_el-Khalili.jpg",[1179,1182,1183],{"time":1180,"text":1181},"Optional","Old Cairo and the Khan el-Khalili bazaar, or leisure on board.",{"time":251,"text":1063},{"time":73,"text":422},{"title":1066,"places":1185,"description":1068,"image":121,"schedule":1186},[405],[1187],{"time":268,"text":695},[1189,1192,1195],{"q":1190,"a":1191},"Why are the sailing times so long?","This is a traditional dahabiya towed by a support tugboat for the long Cairo–Luxor passage. Sailing times are far longer than conventional Nile cruisers — by design. The reward is the slow, authentic river and access to Middle Egypt's rarely-visited monuments.",{"q":1193,"a":1194},"Which direction is faster?","Northbound (Luxor → Cairo) sails with the Nile current and is roughly 15–20% faster than the southbound Cairo → Luxor route. Both visit the same sites; we tailor the direction to your travel plans.",{"q":1196,"a":1197},"What makes this itinerary special?","Very few vessels sail the full Cairo–Luxor reach. You see Giza and the Fayoum pyramids, the painted tombs of Tell el-Amarna and Beni Hassan, and the sacred temples of Abydos and Dendera — alongside the great monuments of Thebes.",[],[1200,1201],"This is a traditional dahabiya towed by a support tugboat for the long Cairo passage — sailing times are far longer than conventional Nile cruisers, by design, for a slow and authentic journey.","The route reaches Middle Egypt's rarely-visited monuments — Fayoum, Tell el-Amarna, and Beni Hassan — alongside the sacred temples of Abydos and Dendera and the great monuments of Thebes.","src/content/itineraries/12n-13d-cairo-luxor.json","275d9cf6b15546c1","7n-8d-aswan-luxor",{"id":1204,"data":1206,"filePath":1230,"digest":1231},{"title":746,"summary":1207,"nights":149,"days":716,"experience":19,"series":20,"vessels":1208,"highlights":1209,"hero":33,"cardImage":753,"routeOverview":1210,"facts":1211,"routes":1214,"faq":1227,"tips":1228,"insights":1229,"featured":139,"comingSoon":139,"draft":139},"A leisurely seven-night sail along the classic Nile route, with time to linger at every temple and island between Aswan and Luxor.",[22,23,24,25],[27,28,29,752,30,31],"Seven unhurried nights on the classic stretch of the Nile, with extra time ashore and on deck. Sailable in either direction.",[1212],{"label":38,"value":1213},"Extended · slow",[1215,1221],{"label":14,"from":45,"to":46,"insights":1216,"timeline":1217},[],[1218],{"title":728,"places":1219,"description":730,"image":33,"schedule":1220},[],[],{"label":845,"from":46,"to":45,"insights":1222,"timeline":1223},[],[1224],{"title":728,"places":1225,"description":730,"image":33,"schedule":1226},[],[],[],[],[],"src/content/itineraries/7n-8d-aswan-luxor.json","0b975655a0b3cbf6","4n-5d-aswan-luxor",{"id":1232,"data":1234,"filePath":1257,"digest":1258},{"title":746,"summary":1235,"nights":18,"days":749,"experience":19,"series":20,"vessels":1236,"highlights":1237,"hero":33,"cardImage":175,"routeOverview":1238,"facts":1239,"routes":1241,"faq":1254,"tips":1255,"insights":1256,"featured":139,"comingSoon":139,"draft":139},"A four-night classic between Aswan and Luxor — the Nile's essential temples at an easy, unhurried pace.",[22,23,24,25],[27,28,29,30,31,32],"Four nights sailing between Aswan and Luxor, taking in Philae, Kom Ombo, Edfu, and the great monuments of Thebes. Sailable in either direction.",[1240],{"label":38,"value":760},[1242,1248],{"label":14,"from":45,"to":46,"insights":1243,"timeline":1244},[],[1245],{"title":728,"places":1246,"description":730,"image":33,"schedule":1247},[],[],{"label":845,"from":46,"to":45,"insights":1249,"timeline":1250},[],[1251],{"title":728,"places":1252,"description":730,"image":33,"schedule":1253},[],[],[],[],[],"src/content/itineraries/4n-5d-aswan-luxor.json","00ba97c0d1306f12","7n-8d-luxor-roundtrip",{"id":1259,"data":1261,"filePath":1283,"digest":1284},{"title":1262,"summary":1263,"nights":149,"days":716,"experience":19,"series":1264,"vessels":1265,"highlights":1266,"hero":104,"cardImage":1268,"routeOverview":1269,"facts":1270,"routes":1273,"faq":1280,"tips":1281,"insights":1282,"featured":139,"comingSoon":139,"draft":139},"Luxor Roundtrip","A seven-night roundtrip from Luxor — sailing south through the temples and back, beginning and ending in the heart of ancient Thebes.","luxor-roundtrip",[22,23,24,25],[31,32,30,29,28,1267],"Esna","/images/luxor_round-trip.jpg","A seven-night roundtrip that begins and ends in Luxor, sailing south to the temples of Esna, Edfu, and Kom Ombo before returning through ancient Thebes — convenient for travellers flying in and out of Luxor.",[1271],{"label":38,"value":1272},"Roundtrip · relaxed",[1274],{"label":1262,"from":46,"to":46,"insights":1275,"timeline":1276},[],[1277],{"title":728,"places":1278,"description":730,"image":104,"schedule":1279},[],[],[],[],[],"src/content/itineraries/7n-8d-luxor-roundtrip.json","451cf1b0da9278f3","journal",["Map",1287,1288],"welcome-aboard",{"id":1287,"data":1289,"body":1297,"filePath":1298,"digest":1299,"rendered":1300},{"title":1290,"excerpt":1291,"date":1292,"author":1293,"tags":1294,"draft":139},"Welcome aboard the journal","A quiet place for stories from the river — what we cook, where we anchor, who we meet, and why we sail the way we do.",["Date","2026-04-01T00:00:00.000Z"],"VEDA Egypt",[1295,1296],"letters","veda","The Nile rewards a slower pace. Over the seasons we've collected stories worth telling — about the kitchen, the crew, the temples, and the small decisions that shape a charter.\n\nThis is where they'll live.\n\nWe'll publish a few times a season — no calendar, no churn. Letters from the boats when something is worth saying.\n\n— The VEDA team","src/content/journal/welcome-aboard.md","1328c4172c08fef4",{"html":1301,"metadata":1302},"\u003Cp>The Nile rewards a slower pace. Over the seasons we’ve collected stories worth telling — about the kitchen, the crew, the temples, and the small decisions that shape a charter.\u003C/p>\n\u003Cp>This is where they’ll live.\u003C/p>\n\u003Cp>We’ll publish a few times a season — no calendar, no churn. Letters from the boats when something is worth saying.\u003C/p>\n\u003Cp>— The VEDA team\u003C/p>",{"headings":1303,"localImagePaths":1304,"remoteImagePaths":1305,"frontmatter":1306,"imagePaths":1309},[],[],[],{"title":1290,"excerpt":1291,"date":1307,"author":1293,"tags":1308},["Date","2026-04-01T00:00:00.000Z"],[1295,1296],[]]